fibomat-0.6.0.dist-info/METADATA
fibomat-0.6.0.dist-info/RECORD
fibomat-0.6.0.dist-info/WHEEL
fibomat-0.6.0.dist-info/entry_points.txt
fibomat/rasterizedpattern.py
fibomat/units.py
fibomat/site.py
fibomat/_libfibomat.pyi
fibomat/_libfibomat.cpython-310-x86_64-linux-gnu.so
fibomat/py.typed
fibomat/__init__.py
fibomat/describable.py
fibomat/sample.py
fibomat/_dimensioned_object.py
fibomat/pattern.py
fibomat/curve_tools/offset.py
fibomat/curve_tools/rasterize.py
fibomat/curve_tools/__init__.py
fibomat/curve_tools/smooth.py
fibomat/curve_tools/intersections.py
fibomat/curve_tools/combine.py
fibomat/curve_tools/biarc_approximation/__init__.py
fibomat/curve_tools/biarc_approximation/spiral_segment.py
fibomat/curve_tools/biarc_approximation/utils.py
fibomat/curve_tools/biarc_approximation/monotone_intervals.py
fibomat/optimize/__init__.py
fibomat/backend/registry.py
fibomat/backend/backendbase.py
fibomat/backend/__init__.py
fibomat/backend/backendbasemeta.py
fibomat/beam_simulation/scalebar.py
fibomat/beam_simulation/window.py
fibomat/beam_simulation/__init__.py
fibomat/beam_simulation/slider.py
fibomat/beam_simulation/markers.py
fibomat/beam_simulation/fibcanvas.py
fibomat/beam_simulation/dwell_time_widget.py
fibomat/mill/mill.py
fibomat/mill/__init__.py
fibomat/mill/ionbeam.py
fibomat/shapes/arc.py
fibomat/shapes/arc_spline.py
fibomat/shapes/hollow_arc_spline.py
fibomat/shapes/line.py
fibomat/shapes/ellipse.py
fibomat/shapes/circle.py
fibomat/shapes/dim_shape.py
fibomat/shapes/polyline.py
fibomat/shapes/biarc.py
fibomat/shapes/text.py
fibomat/shapes/rect.py
fibomat/shapes/ring.py
fibomat/shapes/__init__.py
fibomat/shapes/polygon.py
fibomat/shapes/rasterizedpoints.py
fibomat/shapes/shape.py
fibomat/shapes/_line_non_continuous.py
fibomat/shapes/parametric_curve.py
fibomat/shapes/spot.py
fibomat/raster_styles/scansequence.py
fibomat/raster_styles/rasterstyle.py
fibomat/raster_styles/__init__.py
fibomat/raster_styles/default/__init__.py
fibomat/raster_styles/one_d/__init__.py
fibomat/raster_styles/one_d/curve.py
