Metadata-Version: 2.1
Name: fibomat
Version: 0.6.0
Summary: fib-o-mat is a toolbox to generate patterns for focused ion beam instruments.
Keywords: focused ion beam,fib,pattern,patterning,beam path generation
Author-Email: Victor Deinhart <victor.deinhart@helmholtz-berlin.de>
License: GPLv3
Classifier: Development Status :: 3 - Alpha
Classifier: Programming Language :: Python :: 3 :: Only
Classifier: Programming Language :: Python :: 3.9
Classifier: Programming Language :: Python :: 3.10
Classifier: Programming Language :: Python :: 3.11
Classifier: Programming Language :: Python :: 3.12
Classifier: Programming Language :: Python :: 3.13
Classifier: Programming Language :: C++
Classifier: Topic :: Scientific/Engineering :: Physics
Classifier: License :: OSI Approved :: GNU General Public License v3 (GPLv3)
Classifier: Operating System :: POSIX
Classifier: Operating System :: Microsoft :: Windows
Project-URL: Repository, https://github.com/fib-o-mat/fib-o-mat
Project-URL: Documentation, https://fib-o-mat.readthedocs.io/en/latest/
Requires-Python: >=3.9
Requires-Dist: numpy
Requires-Dist: scipy
Requires-Dist: sympy
Requires-Dist: pint
Requires-Dist: splipy
Requires-Dist: frozenlist
Requires-Dist: pyhershey
Requires-Dist: jinja2
Provides-Extra: exporting
Requires-Dist: bokeh>=3.1.1; extra == "exporting"
Requires-Dist: svgwrite; extra == "exporting"
Requires-Dist: marshmallow; extra == "exporting"
Requires-Dist: prettytable; extra == "exporting"
Requires-Dist: xmltodict; extra == "exporting"
Requires-Dist: colored; extra == "exporting"
Requires-Dist: pillow; extra == "exporting"
Provides-Extra: io
Requires-Dist: svgelements; extra == "io"
Requires-Dist: ezdxf; extra == "io"
Provides-Extra: gui
Requires-Dist: pyqt5; extra == "gui"
Requires-Dist: vispy; extra == "gui"
Provides-Extra: docs
Requires-Dist: setuptools; extra == "docs"
Requires-Dist: sphinx; extra == "docs"
Requires-Dist: recommonmark; extra == "docs"
Requires-Dist: pydata_sphinx_theme; extra == "docs"
Requires-Dist: sphinxemoji; extra == "docs"
Provides-Extra: testing
Requires-Dist: pytest; extra == "testing"
Requires-Dist: pytest-coverage; extra == "testing"
Requires-Dist: pytest-mock; extra == "testing"
Provides-Extra: dev
Requires-Dist: bump2version; extra == "dev"
Requires-Dist: twine; extra == "dev"
